fulcra_context_mcp-0.1.2.dist-info/licenses/LICENSE
fulcra_mcp/__init__.py
fulcra_mcp/main.py
fulcra_context_mcp-0.1.2.dist-info/METADATA
fulcra_context_mcp-0.1.2.dist-info/WHEEL
fulcra_context_mcp-0.1.2.dist-info/entry_points.txt
fulcra_context_mcp-0.1.2.dist-info/top_level.txt
fulcra_context_mcp-0.1.2.dist-info/RECORD
