Metadata-Version: 2.4
Name: fulcra-context-mcp
Version: 0.1.2
Summary: Fulcra Context MCP Server
Author-email: Brandon Creighton <brandon@fulcradynamics.com>
License-Expression: Apache-2.0
Requires-Python: >=3.12
License-File: LICENSE
Requires-Dist: fastapi[standard]>=0.115.12
Requires-Dist: fastmcp>=2.7.0
Requires-Dist: fulcra-api>=0.1.26
Requires-Dist: httpx>=0.28.1
Requires-Dist: mcp[cli]>=1.9.3
Requires-Dist: structlog>=25.4.0
Dynamic: license-file
